gridenc/__init__.py
gridenc/gridenclib.py
gridenc-0.1.2.dist-info/LICENCE
gridenc-0.1.2.dist-info/METADATA
gridenc-0.1.2.dist-info/WHEEL
gridenc-0.1.2.dist-info/top_level.txt
gridenc-0.1.2.dist-info/RECORD
