Metadata-Version: 2.2
Name: gridenc
Version: 0.1.2
Summary: A package to Encrypt and Decrypt a string through grid manipulation
Author-email: Saptak De <saptak1234hehe@gmail.com>
Project-URL: Homepage, https://github.com/sdcard2008/gridenc
Project-URL: Issues, https://github.com/sdcard2008/gridenc/issues
Classifier: Programming Language :: Python :: 3
Classifier: Operating System :: OS Independent
Classifier: License :: OSI Approved :: MIT License
Requires-Python: >=3.8
License-File: LICENCE
